HQGA/__init__.py
HQGA/discretization.py
HQGA/hqga_algorithm.py
HQGA/hqga_utils.py
HQGA/problems.py
HQGA/utils.py
HQGA-0.2.0.dist-info/LICENSE
HQGA-0.2.0.dist-info/METADATA
HQGA-0.2.0.dist-info/WHEEL
HQGA-0.2.0.dist-info/top_level.txt
HQGA-0.2.0.dist-info/RECORD
