Metadata-Version: 2.1
Name: HQGA
Version: 0.2.0
Summary: A library for implementing Hybrid Quantum Genetic Algorithm (HQGA)
Home-page: https://github.com/Quasar-UniNA/HQGA
Author: Autilia Vitiello
Author-email: autilia.vitiello@unina.it
License: MIT
Keywords: Optimization Algorithms,Quantum Computing,Evolutionary Algorithms
Classifier: Development Status :: 3 - Alpha
Classifier: Intended Audience :: Developers
Classifier: Topic :: Software Development :: Build Tools
Classifier: License :: OSI Approved :: MIT License
Classifier: Programming Language :: Python :: 3
License-File: LICENSE
Requires-Dist: matplotlib
Requires-Dist: numpy
Requires-Dist: openpyxl (==3.1.2)
Requires-Dist: qiskit (==0.42.0)
Requires-Dist: qiskit-aer (==0.12.0)
Requires-Dist: qiskit-ibmq-provider (==0.20.2)
Requires-Dist: qiskit-terra (==0.23.2)
Requires-Dist: sympy
Requires-Dist: tqdm
